{
    "businesses": [
        {
            "alias": "zandras-taqueria-fairfax",
            "categories": [
                {
                    "alias": "tacos",
                    "title": "Tacos"
                }
            ],
            "coordinates": {
                "latitude": 38.84712,
                "longitude": -77.30507
            },
            "display_phone": "(571) 359-6767",
            "distance": 1179.9341347257323,
            "id": "DPcW5WPfYIWdPhENj_unrQ",
            "image_url": "https://s3-media4.fl.yelpcdn.com/bphoto/PiBdxzNkz6rkl1o_1GsU7A/o.jpg",
            "is_closed": false,
            "location": {
                "address1": "3950 University Dr",
                "address2": "Ste 210",
                "address3": "",
                "city": "Fairfax",
                "country": "US",
                "display_address": [
                    "3950 University Dr",
                    "Ste 210",
                    "Fairfax, VA 22030"
                ],
                "state": "VA",
                "zip_code": "22030"
            },
            "name": "Zandra's Taqueria",
            "phone": "+15713596767",
            "rating": 4.5,
            "review_count": 29,
            "transactions": [],
            "url": "https://www.yelp.com/biz/zandras-taqueria-fairfax?adjust_creative=wBW6HE4nirReynin1fNGKA&utm_campaign=yelp_api_v3&utm_medium=api_v3_business_search&utm_source=wBW6HE4nirReynin1fNGKA"
        },
        {
            "alias": "ornery-beer-company-fairfax",
            "categories": [
                {
                    "alias": "tradamerican",
                    "title": "American (Traditional)"
                },
                {
                    "alias": "brewpubs",
                    "title": "Brewpubs"
                },
                {
                    "alias": "pubs",
                    "title": "Pubs"
                }
            ],
            "coordinates": {
                "latitude": 38.84712,
                "longitude": -77.30507
            },
            "display_phone": "(571) 459-2143",
            "distance": 1179.9341347257323,
            "id": "gx5kGdZwjOwa9aCPkfL7uQ",
            "image_url": "https://s3-media3.fl.yelpcdn.com/bphoto/s7wF3cPYZ0-dWHsd9BjoEA/o.jpg",
            "is_closed": false,
            "location": {
                "address1": "3950 University Dr",
                "address2": "Ste 209",
                "address3": "",
                "city": "Fairfax",
                "country": "US",
                "display_address": [
                    "3950 University Dr",
                    "Ste 209",
                    "Fairfax, VA 22030"
                ],
                "state": "VA",
                "zip_code": "22030"
            },
            "name": "Ornery Beer Company",
            "phone": "+15714592143",
            "rating": 4.0,
            "review_count": 11,
            "transactions": [],
            "url": "https://www.yelp.com/biz/ornery-beer-company-fairfax?adjust_creative=wBW6HE4nirReynin1fNGKA&utm_campaign=yelp_api_v3&utm_medium=api_v3_business_search&utm_source=wBW6HE4nirReynin1fNGKA"
        },
        {
            "alias": "taco-bamba-fairfax-2",
            "categories": [
                {
                    "alias": "tacos",
                    "title": "Tacos"
                }
            ],
            "coordinates": {
                "latitude": 38.8261692,
                "longitude": -77.3139017
            },
            "display_phone": "(571) 655-6265",
            "distance": 1558.890275961376,
            "id": "gAJGEoaUVm-48tBGSZ9JPg",
            "image_url": "https://s3-media4.fl.yelpcdn.com/bphoto/PcTP-obSt2fBu5JWFDsL_A/o.jpg",
            "is_closed": false,
            "location": {
                "address1": "10629 Braddock Rd",
                "address2": "",
                "address3": null,
                "city": "Fairfax",
                "country": "US",
                "display_address": [
                    "10629 Braddock Rd",
                    "Fairfax, VA 22032"
                ],
                "state": "VA",
                "zip_code": "22032"
            },
            "name": "Taco Bamba",
            "phone": "+15716556265",
            "rating": 4.0,
            "review_count": 21,
            "transactions": [],
            "url": "https://www.yelp.com/biz/taco-bamba-fairfax-2?adjust_creative=wBW6HE4nirReynin1fNGKA&utm_campaign=yelp_api_v3&utm_medium=api_v3_business_search&utm_source=wBW6HE4nirReynin1fNGKA"
        },
        {
            "alias": "the-nail-bar-fairfax-2",
            "categories": [
                {
                    "alias": "othersalons",
                    "title": "Nail Salons"
                },
                {
                    "alias": "waxing",
                    "title": "Waxing"
                },
                {
                    "alias": "skincare",
                    "title": "Skin Care"
                }
            ],
            "coordinates": {
                "latitude": 38.852484,
                "longitude": -77.327639
            },
            "display_phone": "(571) 459-2729",
            "distance": 1911.1101624293594,
            "id": "yYt3rDPLlnCviwe4UA9c-Q",
            "image_url": "https://s3-media4.fl.yelpcdn.com/bphoto/4_Qii9T6_Ifpj_VO4LkifQ/o.jpg",
            "is_closed": false,
            "location": {
                "address1": "11060 Lee Hwy",
                "address2": null,
                "address3": "",
                "city": "Fairfax",
                "country": "US",
                "display_address": [
                    "11060 Lee Hwy",
                    "Fairfax, VA 22030"
                ],
                "state": "VA",
                "zip_code": "22030"
            },
            "name": "The Nail Bar",
            "phone": "+15714592729",
            "rating": 4.0,
            "review_count": 20,
            "transactions": [],
            "url": "https://www.yelp.com/biz/the-nail-bar-fairfax-2?adjust_creative=wBW6HE4nirReynin1fNGKA&utm_campaign=yelp_api_v3&utm_medium=api_v3_business_search&utm_source=wBW6HE4nirReynin1fNGKA"
        },
        {
            "alias": "pho4ever-fairfax-3",
            "categories": [
                {
                    "alias": "vietnamese",
                    "title": "Vietnamese"
                }
            ],
            "coordinates": {
                "latitude": 38.84414,
                "longitude": -77.2908
            },
            "display_phone": "(703) 691-0090",
            "distance": 2051.7827556052894,
            "id": "KTpPFjlIjcAL7g72NkWgXw",
            "image_url": "https://s3-media4.fl.yelpcdn.com/bphoto/ppgdlQQaquG5Mlp4l5mpxw/o.jpg",
            "is_closed": false,
            "location": {
                "address1": "9966 Main St",
                "address2": null,
                "address3": "",
                "city": "Fairfax",
                "country": "US",
                "display_address": [
                    "9966 Main St",
                    "Fairfax, VA 22031"
                ],
                "state": "VA",
                "zip_code": "22031"
            },
            "name": "Pho4ever",
            "phone": "+17036910090",
            "rating": 5.0,
            "review_count": 21,
            "transactions": [],
            "url": "https://www.yelp.com/biz/pho4ever-fairfax-3?adjust_creative=wBW6HE4nirReynin1fNGKA&utm_campaign=yelp_api_v3&utm_medium=api_v3_business_search&utm_source=wBW6HE4nirReynin1fNGKA"
        },
        {
            "alias": "senor-tequilas-fairfax",
            "categories": [
                {
                    "alias": "mexican",
                    "title": "Mexican"
                }
            ],
            "coordinates": {
                "latitude": 38.843084,
                "longitude": -77.290547
            },
            "display_phone": "(703) 543-4494",
            "distance": 2055.532767146114,
            "id": "OzOxIB93QWAUmCkkUemwqg",
            "image_url": "https://s3-media2.fl.yelpcdn.com/bphoto/ZgpLYIPVLLUWMFOrhI1q4A/o.jpg",
            "is_closed": false,
            "location": {
                "address1": "9959 Main St",
                "address2": "",
                "address3": null,
                "city": "Fairfax",
                "country": "US",
                "display_address": [
                    "9959 Main St",
                    "Fairfax, VA 22031"
                ],
                "state": "VA",
                "zip_code": "22031"
            },
            "name": "Senor Tequila's",
            "phone": "+17035434494",
            "rating": 3.5,
            "review_count": 39,
            "transactions": [
                "delivery",
                "pickup"
            ],
            "url": "https://www.yelp.com/biz/senor-tequilas-fairfax?adjust_creative=wBW6HE4nirReynin1fNGKA&utm_campaign=yelp_api_v3&utm_medium=api_v3_business_search&utm_source=wBW6HE4nirReynin1fNGKA"
        },
        {
            "alias": "sushi-plus-fairfax",
            "categories": [
                {
                    "alias": "sushi",
                    "title": "Sushi Bars"
                },
                {
                    "alias": "asianfusion",
                    "title": "Asian Fusion"
                },
                {
                    "alias": "breakfast_brunch",
                    "title": "Breakfast & Brunch"
                }
            ],
            "coordinates": {
                "latitude": 38.8559,
                "longitude": -77.33029
            },
            "display_phone": "(571) 459-2950",
            "distance": 2327.8459498713623,
            "id": "7SWNu9vYJiGVY03bgkEqwg",
            "image_url": "https://s3-media2.fl.yelpcdn.com/bphoto/iCaSDoQiK-AvGIc9cwnUcg/o.jpg",
            "is_closed": false,
            "location": {
                "address1": "11166 Fairfax Blvd",
                "address2": "Ste 102",
                "address3": "",
                "city": "Fairfax",
                "country": "US",
                "display_address": [
                    "11166 Fairfax Blvd",
                    "Ste 102",
                    "Fairfax, VA 22030"
                ],
                "state": "VA",
                "zip_code": "22030"
            },
            "name": "Sushi Plus",
            "phone": "+15714592950",
            "rating": 5.0,
            "review_count": 3,
            "transactions": [],
            "url": "https://www.yelp.com/biz/sushi-plus-fairfax?adjust_creative=wBW6HE4nirReynin1fNGKA&utm_campaign=yelp_api_v3&utm_medium=api_v3_business_search&utm_source=wBW6HE4nirReynin1fNGKA"
        },
        {
            "alias": "simply-social-coffee-fairfax-3",
            "categories": [
                {
                    "alias": "coffee",
                    "title": "Coffee & Tea"
                },
                {
                    "alias": "breakfast_brunch",
                    "title": "Breakfast & Brunch"
                },
                {
                    "alias": "sandwiches",
                    "title": "Sandwiches"
                }
            ],
            "coordinates": {
                "latitude": 38.85472,
                "longitude": -77.33489
            },
            "display_phone": "(703) 239-6889",
            "distance": 2490.3933308447126,
            "id": "lRZxTs3CEuIve1NSuPWmwg",
            "image_url": "https://s3-media2.fl.yelpcdn.com/bphoto/481LgSAyqE7LEWyywZZPJA/o.jpg",
            "is_closed": false,
            "location": {
                "address1": "11282 James Swart Cir",
                "address2": null,
                "address3": "",
                "city": "Fairfax",
                "country": "US",
                "display_address": [
                    "11282 James Swart Cir",
                    "Fairfax, VA 22030"
                ],
                "state": "VA",
                "zip_code": "22030"
            },
            "name": "Simply Social Coffee",
            "phone": "+17032396889",
            "rating": 5.0,
            "review_count": 76,
            "transactions": [],
            "url": "https://www.yelp.com/biz/simply-social-coffee-fairfax-3?adjust_creative=wBW6HE4nirReynin1fNGKA&utm_campaign=yelp_api_v3&utm_medium=api_v3_business_search&utm_source=wBW6HE4nirReynin1fNGKA"
        },
        {
            "alias": "shilla-bakery-fairfax-2",
            "categories": [
                {
                    "alias": "desserts",
                    "title": "Desserts"
                },
                {
                    "alias": "coffee",
                    "title": "Coffee & Tea"
                },
                {
                    "alias": "bakeries",
                    "title": "Bakeries"
                }
            ],
            "coordinates": {
                "latitude": 38.8623158807625,
                "longitude": -77.3560741539711
            },
            "display_phone": "(703) 459-2400",
            "distance": 4483.338372298784,
            "id": "kQhawX2bIiE6JifsvXHPdw",
            "image_url": "https://s3-media4.fl.yelpcdn.com/bphoto/vRzxFAVpr2DXqyycibvRvw/o.jpg",
            "is_closed": false,
            "location": {
                "address1": "11750 Fair Oaks Mall",
                "address2": "",
                "address3": null,
                "city": "Fairfax",
                "country": "US",
                "display_address": [
                    "11750 Fair Oaks Mall",
                    "Fairfax, VA 22033"
                ],
                "state": "VA",
                "zip_code": "22033"
            },
            "name": "Shilla Bakery",
            "phone": "+17034592400",
            "rating": 4.5,
            "review_count": 4,
            "transactions": [],
            "url": "https://www.yelp.com/biz/shilla-bakery-fairfax-2?adjust_creative=wBW6HE4nirReynin1fNGKA&utm_campaign=yelp_api_v3&utm_medium=api_v3_business_search&utm_source=wBW6HE4nirReynin1fNGKA"
        },
        {
            "alias": "dc-lash-bar-arlington-arlington",
            "categories": [
                {
                    "alias": "eyelashservice",
                    "title": "Eyelash Service"
                },
                {
                    "alias": "spraytanning",
                    "title": "Spray Tanning"
                },
                {
                    "alias": "hairremoval",
                    "title": "Hair Removal"
                }
            ],
            "coordinates": {
                "latitude": 38.87984,
                "longitude": -77.11131
            },
            "display_phone": "(571) 312-8891",
            "distance": 18098.8092014987,
            "id": "68oBMNcgZJ8-zrfMrwRiUw",
            "image_url": "https://s3-media3.fl.yelpcdn.com/bphoto/ztRMfITbCb0thzTpl_dbAA/o.jpg",
            "is_closed": false,
            "location": {
                "address1": "4238 Wilson Blvd",
                "address2": "Ste 1150",
                "address3": "",
                "city": "Arlington",
                "country": "US",
                "display_address": [
                    "4238 Wilson Blvd",
                    "Ste 1150",
                    "Arlington, VA 22203"
                ],
                "state": "VA",
                "zip_code": "22203"
            },
            "name": "DC Lash Bar- Arlington",
            "phone": "+15713128891",
            "rating": 5.0,
            "review_count": 5,
            "transactions": [],
            "url": "https://www.yelp.com/biz/dc-lash-bar-arlington-arlington?adjust_creative=wBW6HE4nirReynin1fNGKA&utm_campaign=yelp_api_v3&utm_medium=api_v3_business_search&utm_source=wBW6HE4nirReynin1fNGKA"
        }
    ],
    "region": {
        "center": {
            "latitude": 38.8394626834737,
            "longitude": -77.31342085918524
        }
    },
    "total": 10
}